{
    "webInfo":{
        "name":"阿尔法量化",
        "des":"全球数字货币一站式量化交易平台",
        "helloInfo":"轻松量化 聪明套利"
    },
    "pageList":["home","server","page3","page4","page5","page6"],
    "navList":[
        {"id":0,"pageIndex":"home","name":"首页"},
        {"id":1,"pageIndex":"server","name":"产品与服务"},
        {"id":2,"pageIndex":"page3","name":"优势与特色"},
        {"id":3,"pageIndex":"page4","name":"接入交易所"},
        {"id":4,"pageIndex":"page5","name":"问题与帮助"},
        {"id":5,"pageIndex":"page6","name":"关于我们"}
    ],
    "footerInfo":{
        "business":{
            "title":"业务合作",
            "list":[
                {"lab":"微信：","val":"taolibao888"},
                {"lab":"邮箱：","val":"banzhuantaolibao@163.com"},
                {"lab":"电话：","val":"17600162266"}
            ]
        },
        "contact":{
            "title":"联系地址",
            "list":[
                {"lab":"总部地址：","val":"厦门市海沧区海景东路18号1楼8116"},
                {"lab":"分部地址：","val":"厦门市湖里区创新路2号兴联电子大厦三楼S2区"}
            ]
        },
        "attention":{
            "title":"关注我们"
        },
        "copyright":{
            "icp":"Copyright © Alpha",
            "name":"阿尔法"
        }
    },
    "forTraders":{
      "title":"产品与服务",
      "注意":"下面的class值是对应显示的图标，图标列表这里http://element-cn.eleme.io/#/zh-CN/component/icon",
      "list":[
        {"title":"行情监测","content":"7*24小时自动监测行情不放过每一毫秒套利机会","class":"el-icon-view"},
        {"title":"两角套利","content":"两个交易所间相同交易对之间的无风险对冲套利","class":"el-icon-share"},
        {"title":"三角套利","content":"多个交易所间不同交易对之间的无风险对冲套利","class":"el-icon-news"},
        {"title":"站内套利","content":"同一个交易所不同交易对之间的无风险对冲套利","class":"el-icon-tickets"},
        {"title":"趋势套利","content":"多个交易所不同线趋势变化实时分析全自动交易","class":"el-icon-menu"},
        {"title":"投研报告","content":"精准挖掘海量行情数据好收益来自好的投研报告","class":"el-icon-mobile-phone"},
        {"title":"账户管家","content":"一点登录监控管理所有交易所币种账户动态变化","class":"el-icon-setting"},
        {"title":"套利社群","content":"汇聚行业大咖、矿主、项目方只谈赚币不谈情怀","class":"el-icon-upload"}
      ] 
    },
    "exchange":{
      "title":"优势与特色",
      "desList":[
		"量价挖掘更准, 风险控制更稳,行情捕捉更多,交易速度更快","所以套利收益更高"
      ],
      "list":[
        {"title": "安全","content":"银行级加密，资金仅存放您的交易所账户内，完全由您掌控"},
	    {"title": "简单","content": "一点登录简单配置，轻松开启全球量化套利，同时管理多个账户数字资产"},
        {"title": "智能","content": "7*24小时自动监测行情，全自动交易无需盯盘。"},
        {"title": "全面","content": "未来将覆盖全球100+交易所，1000+数字资产，100000+交易组合"}
      ] 
    },
    "teamInfo":{
        "title":"团队介绍",
        "desList":[
          "阿尔法创始团队",
          "成功管理超过400亿资产",
          "核心成员毕业知名院校金融，计算机专业",
          "具有多年金融行业投资，研发，运营经验",
          "以‘轻松量化，聪明投资’ 做为使命",
          "秉承‘用户至上’的服务宗旨",
          "致力于打造全球数字货币量化交易平台为愿景",
          "为您的数字资产保驾护航"
        ],
        "newInfo":{
            "title": "媒体报道",
            "list":[
                {
                    "title":"阿尔法套利宝AbrBao推出数字货币自动交易软件机器人",
                    "link":"https://baijiahao.baidu.com/s?id=1612777810561073441&wfr=spider&for=pc"
                },
                {
                    "title":"数字货币量化搬砖套利详解（史上最全）",
                    "link":"http://www.weilaicaijing.com/article/15184"
                },
                {
                    "title":"阿尔法：今日搬砖套利1.29万USDT 如果我们都死了 他仍将继续交易",
                    "link":"https://www.jinse.com/bitcoin/254579.html"
                }
              ]
            }
      },
    "ourPartners":{
      "title":"合作交易所",
      "list":[
        {"title":"Huobi","content":"不要文本和标题留空就行"},
        {"title":"Okex","content":"不要文本和标题留空就行"},
        {"title":"Binance","content":"不要文本和标题留空就行"},
        {"title":"ZB","content":"不要文本和标题留空就行"},
        {"title":"Fcoin","content":"不要文本和标题留空就行"},
        {"title":"Gate","content":"不要文本和标题留空就行"},
        {"title":"Exx","content":"不要文本和标题留空就行"},
        {"title":"Hadax","content":"不要文本和标题留空就行"}
      ] 
    }
}








